huaweicloudsdkcsms/__init__.py
huaweicloudsdkcsms/v1/__init__.py
huaweicloudsdkcsms/v1/csms_async_client.py
huaweicloudsdkcsms/v1/csms_client.py
huaweicloudsdkcsms/v1/model/__init__.py
huaweicloudsdkcsms/v1/model/action_resources.py
huaweicloudsdkcsms/v1/model/agency.py
huaweicloudsdkcsms/v1/model/batch_create_or_delete_tags_request.py
huaweicloudsdkcsms/v1/model/batch_create_or_delete_tags_request_body.py
huaweicloudsdkcsms/v1/model/batch_create_or_delete_tags_response.py
huaweicloudsdkcsms/v1/model/batch_import_secrets_request.py
huaweicloudsdkcsms/v1/model/batch_import_secrets_response.py
huaweicloudsdkcsms/v1/model/change_users_password.py
huaweicloudsdkcsms/v1/model/check_secrets_request.py
huaweicloudsdkcsms/v1/model/check_secrets_request_body.py
huaweicloudsdkcsms/v1/model/check_secrets_response.py
huaweicloudsdkcsms/v1/model/create_agency_request.py
huaweicloudsdkcsms/v1/model/create_agency_request_body.py
huaweicloudsdkcsms/v1/model/create_agency_response.py
huaweicloudsdkcsms/v1/model/create_grants_request.py
huaweicloudsdkcsms/v1/model/create_grants_response.py
huaweicloudsdkcsms/v1/model/create_password_request_body.py
huaweicloudsdkcsms/v1/model/create_secret_event_request.py
huaweicloudsdkcsms/v1/model/create_secret_event_request_body.py
huaweicloudsdkcsms/v1/model/create_secret_event_response.py
huaweicloudsdkcsms/v1/model/create_secret_request.py
huaweicloudsdkcsms/v1/model/create_secret_request_body.py
huaweicloudsdkcsms/v1/model/create_secret_response.py
huaweicloudsdkcsms/v1/model/create_secret_tag_request.py
huaweicloudsdkcsms/v1/model/create_secret_tag_request_body.py
huaweicloudsdkcsms/v1/model/create_secret_tag_response.py
huaweicloudsdkcsms/v1/model/create_secret_version_request.py
huaweicloudsdkcsms/v1/model/create_secret_version_request_body.py
huaweicloudsdkcsms/v1/model/create_secret_version_response.py
huaweicloudsdkcsms/v1/model/delete_grant_request.py
huaweicloudsdkcsms/v1/model/delete_grant_response.py
huaweicloudsdkcsms-3.1.184.dist-info/METADATA
huaweicloudsdkcsms-3.1.184.dist-info/WHEEL
huaweicloudsdkcsms-3.1.184.dist-info/licenses/LICENSE
huaweicloudsdkcsms-3.1.184.dist-info/RECORD
